lightly_studio/__init__.py
lightly_studio/db_manager.py
lightly_studio/errors.py
lightly_studio/export_schema.py
lightly_studio/export_version.py
lightly_studio/py.typed
lightly_studio/setup_logging.py
lightly_studio/type_definitions.py
lightly_studio/api/__init__.py
lightly_studio/api/app.py
lightly_studio/api/cache.py
lightly_studio/api/db_tables.py
lightly_studio/api/features.py
lightly_studio/api/server.py
lightly_studio/api/routes/healthz.py
lightly_studio/api/routes/images.py
lightly_studio/api/routes/video_frames_media.py
lightly_studio/api/routes/video_media.py
lightly_studio/api/routes/webapp.py
lightly_studio/api/routes/api/annotation.py
lightly_studio/api/routes/api/annotation_label.py
lightly_studio/api/routes/api/caption.py
lightly_studio/api/routes/api/classifier.py
lightly_studio/api/routes/api/collection.py
lightly_studio/api/routes/api/collection_tag.py
lightly_studio/api/routes/api/embeddings2d.py
lightly_studio/api/routes/api/exceptions.py
lightly_studio/api/routes/api/export.py
lightly_studio/api/routes/api/features.py
lightly_studio/api/routes/api/frame.py
lightly_studio/api/routes/api/image.py
lightly_studio/api/routes/api/image_embedding.py
lightly_studio/api/routes/api/metadata.py
lightly_studio/api/routes/api/operator.py
lightly_studio/api/routes/api/sample.py
lightly_studio/api/routes/api/selection.py
lightly_studio/api/routes/api/settings.py
lightly_studio/api/routes/api/status.py
lightly_studio/api/routes/api/text_embedding.py
lightly_studio/api/routes/api/validators.py
lightly_studio/api/routes/api/video.py
lightly_studio/api/routes/api/annotations/__init__.py
lightly_studio/api/routes/api/annotations/create_annotation.py
lightly_studio/core/__init__.py
lightly_studio/core/add_samples.py
lightly_studio/core/add_videos.py
lightly_studio/core/dataset.py
lightly_studio/core/db_field.py
lightly_studio/core/image_dataset.py
lightly_studio/core/image_sample.py
lightly_studio/core/loading_log.py
lightly_studio/core/sample.py
lightly_studio-0.4.7.dist-info/METADATA
lightly_studio-0.4.7.dist-info/WHEEL
lightly_studio-0.4.7.dist-info/RECORD
