Metadata-Version: 2.4
Name: lightly-studio
Version: 0.4.7
Summary: LightlyStudio is a lightweight, fast, and easy-to-use data exploration tool for data scientists and engineers.
Classifier: Operating System :: MacOS :: MacOS X
Classifier: Operating System :: Microsoft :: Windows
Classifier: Operating System :: POSIX :: Linux
Classifier: Programming Language :: Python :: 3
Classifier: Programming Language :: Python :: 3.8
Classifier: Programming Language :: Python :: 3.9
Classifier: Programming Language :: Python :: 3.10
Classifier: Programming Language :: Python :: 3.11
Classifier: Programming Language :: Python :: 3.12
Classifier: Programming Language :: Python :: 3.13
Requires-Python: <3.14,>=3.8
Requires-Dist: annotated-types==0.7.0
Requires-Dist: av>=10.0.0
Requires-Dist: duckdb-engine<0.17,>=0.15.0
Requires-Dist: duckdb<1.3,>=1.2.2
Requires-Dist: einops>=0.6.0
Requires-Dist: environs<12.0.0
Requires-Dist: eval-type-backport>=0.2.2
Requires-Dist: fastapi>=0.115.5
Requires-Dist: faster-coco-eval>=1.6.5
Requires-Dist: fsspec>=2023.1.0
Requires-Dist: labelformat>=0.1.10
Requires-Dist: lightly-mundig==0.1.9
Requires-Dist: open-clip-torch>=2.20.0
Requires-Dist: opencv-python-headless>=4.11.0.86
Requires-Dist: pyarrow>=17.0.0
Requires-Dist: python-multipart>=0.0.20
Requires-Dist: requests>=2.32.3
Requires-Dist: scikit-learn==1.3.2; python_version < '3.10'
Requires-Dist: scikit-learn==1.7.2; python_version >= '3.10'
Requires-Dist: sqlmodel>=0.0.22
Requires-Dist: torch<2.6.0; python_version < '3.9'
Requires-Dist: torch>=2.6.0; python_version >= '3.9'
Requires-Dist: torchvision<0.20.0; python_version < '3.9'
Requires-Dist: torchvision>=0.20.0; python_version >= '3.9'
Requires-Dist: tqdm>=4.65.0
Requires-Dist: typing-extensions>=4.12.2
Requires-Dist: uvicorn>=0.32.1
Requires-Dist: xxhash>=3.5.0
Provides-Extra: cloud-storage
Requires-Dist: adlfs>=2023.1.0; extra == 'cloud-storage'
Requires-Dist: gcsfs>=2023.1.0; extra == 'cloud-storage'
Requires-Dist: s3fs>=2023.1.0; extra == 'cloud-storage'
Provides-Extra: lightly-edge
Requires-Dist: lightly-edge-sdk>=1.0.3.post1; extra == 'lightly-edge'
